wordfreq/__init__.py
wordfreq/chinese.py
wordfreq/data/_chinese_mapping.msgpack.gz
wordfreq/data/jieba_zh.txt
wordfreq/data/jieba_zh_orig.txt
wordfreq/data/large_ar.msgpack.gz
wordfreq/data/large_bn.msgpack.gz
wordfreq/data/large_ca.msgpack.gz
wordfreq/data/large_cs.msgpack.gz
wordfreq/data/large_de.msgpack.gz
wordfreq/data/large_en.msgpack.gz
wordfreq/data/large_es.msgpack.gz
wordfreq/data/large_fi.msgpack.gz
wordfreq/data/large_fr.msgpack.gz
wordfreq/data/large_he.msgpack.gz
wordfreq/data/large_it.msgpack.gz
wordfreq/data/large_ja.msgpack.gz
wordfreq/data/large_mk.msgpack.gz
wordfreq/data/large_nb.msgpack.gz
wordfreq/data/large_nl.msgpack.gz
wordfreq/data/large_pl.msgpack.gz
wordfreq/data/large_pt.msgpack.gz
wordfreq/data/large_ru.msgpack.gz
wordfreq/data/large_sv.msgpack.gz
wordfreq/data/large_uk.msgpack.gz
wordfreq/data/large_zh.msgpack.gz
wordfreq/data/small_ar.msgpack.gz
wordfreq/data/small_bg.msgpack.gz
wordfreq/data/small_bn.msgpack.gz
wordfreq/data/small_ca.msgpack.gz
wordfreq/data/small_cs.msgpack.gz
wordfreq/data/small_da.msgpack.gz
wordfreq/data/small_de.msgpack.gz
wordfreq/data/small_el.msgpack.gz
wordfreq/data/small_en.msgpack.gz
wordfreq/data/small_es.msgpack.gz
wordfreq/data/small_fa.msgpack.gz
wordfreq/data/small_fi.msgpack.gz
wordfreq/data/small_fil.msgpack.gz
wordfreq/data/small_fr.msgpack.gz
wordfreq/data/small_he.msgpack.gz
wordfreq/data/small_hi.msgpack.gz
wordfreq/data/small_hu.msgpack.gz
wordfreq/data/small_id.msgpack.gz
wordfreq/data/small_is.msgpack.gz
wordfreq/data/small_it.msgpack.gz
wordfreq/data/small_ja.msgpack.gz
wordfreq/data/small_ko.msgpack.gz
wordfreq/data/small_lt.msgpack.gz
wordfreq/data/small_lv.msgpack.gz
wordfreq/data/small_mk.msgpack.gz
wordfreq/data/small_ms.msgpack.gz
wordfreq/data/small_nb.msgpack.gz
wordfreq/data/small_nl.msgpack.gz
wordfreq/data/small_pl.msgpack.gz
wordfreq/data/small_pt.msgpack.gz
wordfreq/data/small_ro.msgpack.gz
wordfreq/data/small_ru.msgpack.gz
wordfreq/data/small_sh.msgpack.gz
wordfreq-3.1.0.dist-info/LICENSE.txt
wordfreq-3.1.0.dist-info/METADATA
wordfreq-3.1.0.dist-info/WHEEL
wordfreq-3.1.0.dist-info/RECORD
