Metadata-Version: 2.1
Name: wordfreq
Version: 3.1.0
Summary: Look up the frequencies of words in many languages, based on many sources of data.
Home-page: https://github.com/rspeer/wordfreq/
License: Apache-2.0
Author: Robyn Speer
Author-email: rspeer@arborelia.net
Requires-Python: >=3.8,<4
Classifier: License :: OSI Approved :: Apache Software License
Classifier: Programming Language :: Python :: 3
Classifier: Programming Language :: Python :: 3.8
Classifier: Programming Language :: Python :: 3.9
Classifier: Programming Language :: Python :: 3.10
Classifier: Programming Language :: Python :: 3.11
Provides-Extra: cjk
Provides-Extra: jieba
Provides-Extra: mecab
Requires-Dist: ftfy (>=6.1)
Requires-Dist: ipadic (>=1.0.0,<2.0.0) ; extra == "cjk" or extra == "mecab"
Requires-Dist: jieba (>=0.42) ; extra == "cjk" or extra == "jieba"
Requires-Dist: langcodes (>=3.0)
Requires-Dist: locate (>=1.1.1,<2.0.0)
Requires-Dist: mecab-ko-dic (>=1.0.0,<2.0.0) ; extra == "cjk" or extra == "mecab"
Requires-Dist: mecab-python3 (>=1.0.5,<2.0.0) ; extra == "cjk" or extra == "mecab"
Requires-Dist: msgpack (>=1.0.7,<2.0.0)
Requires-Dist: regex (>=2023.10.3)
